{
  "ID": "dc61125c-ddd1-4c30-b7c2-aa7e5ef205e7",
  "Version": "2.3.2.0",
  "Name": "game",
  "Content": {
    "Content": {
      "Animation": {
        "Duration": 0,
        "Speed": 1.0,
        "Timelines": [],
        "ctype": "TimelineActionData"
      },
      "AnimationList": [],
      "ObjectData": {
        "Tag": 4,
        "Children": [
          {
            "FontSize": 14,
            "ButtonText": "Button",
            "TextColor": {
              "R": 65,
              "G": 65,
              "B": 70
            },
            "DisabledFileData": {
              "Type": "Default",
              "Path": "Default/Button_Disable.png",
              "Plist": ""
            },
            "PressedFileData": {
              "Type": "Default",
              "Path": "Default/Button_Press.png",
              "Plist": ""
            },
            "NormalFileData": {
              "Type": "Default",
              "Path": "Default/Button_Normal.png",
              "Plist": ""
            },
            "Scale9Enable": true,
            "Scale9OriginX": 15,
            "Scale9OriginY": 11,
            "Scale9Width": 16,
            "Scale9Height": 14,
            "OutlineColor": {
              "G": 0,
              "B": 0
            },
            "ShadowColor": {
              "R": 110,
              "G": 110,
              "B": 110
            },
            "ShadowOffsetX": 2.0,
            "ShadowOffsetY": -2.0,
            "TouchEnable": true,
            "AnchorPoint": {
              "ScaleX": 0.5,
              "ScaleY": 0.5
            },
            "Position": {
              "X": 205.6476,
              "Y": 570.6257
            },
            "Scale": {
              "ScaleX": 1.0,
              "ScaleY": 1.0
            },
            "CColor": {},
            "IconVisible": false,
            "PrePosition": {
              "X": 0.3213,
              "Y": 0.5944
            },
            "PreSize": {
              "X": 0.0,
              "Y": 0.0
            },
            "LeftMargin": 182.6476,
            "RightMargin": 411.3524,
            "TopMargin": 371.3743,
            "BottomMargin": 552.6257,
            "CallBackType": "Click",
            "CallBackName": "onAA",
            "Tag": 7,
            "ActionTag": 1184873524,
            "Size": {
              "X": 46.0,
              "Y": 36.0
            },
            "Name": "Button_1",
            "ctype": "ButtonObjectData"
          }
        ],
        "Size": {
          "X": 640.0,
          "Y": 960.0
        },
        "Name": "Scene",
        "ctype": "SingleNodeObjectData"
      },
      "UsedResources": [
        "Default/Button_Disable.png",
        "Default/Button_Normal.png",
        "Default/Button_Press.png"
      ],
      "ctype": "GameProjectData"
    }
  },
  "Type": "Scene"
}