{
  "10001": {
    "name": "战役1",
    "next": "10002",
    "icon": "10001",
    "bonus": [
      {
        "unit": "gold",
        "value": 100
      }
    ],
    "battleNum": 12,
    "enemyTypes": [
      {
        "id": "1001",
        "lv": 1
      },
      {
        "id": "1001",
        "lv": 2
      },
      {
        "id": "1001",
        "lv": 3
      }
    ],
    "enemyNumMin": 3,
    "enemyNumMax": 5,
    "bossBattle": [
      {
        "id": "1001",
        "lv": 1
      },
      {
        "id": "1002",
        "lv": 5
      },
      {
        "id": "1002",
        "lv": 5
      }
    ]
  },
  "10002": {
    "name": "战役2",
    "icon": "10002",
    "next": "10003",
    "bonus": [
      {
        "unit": "gold",
        "value": 100
      }
    ],
    "battleNum": 12,
    "enemyTypes": [
      {
        "id": "1001",
        "lv": 1
      },
      {
        "id": "1001",
        "lv": 2
      },
      {
        "id": "1001",
        "lv": 3
      }
    ],
    "enemyNumMin": 3,
    "enemyNumMax": 5,
    "bossBattle": [
      {
        "id": "1001",
        "lv": 1
      },
      {
        "id": "1002",
        "lv": 5
      },
      {
        "id": "1002",
        "lv": 5
      }
    ]
  }
}