{
  "ID": "474cb21c-348b-43b6-a7ae-dfa2f1f2a19d",
  "Version": "2.3.3.0",
  "Name": "RankView",
  "Content": {
    "Content": {
      "Animation": {
        "Duration": 0,
        "Speed": 1.0,
        "Timelines": [],
        "ctype": "TimelineActionData"
      },
      "AnimationList": [],
      "ObjectData": {
        "Tag": 40,
        "Children": [
          {
            "BackColorAlpha": 102,
            "SingleColor": {
              "R": 150,
              "G": 200
            },
            "FirstColor": {
              "R": 150,
              "G": 200
            },
            "EndColor": {},
            "ColorVector": {
              "ScaleY": 1.0
            },
            "Scale9Width": 1,
            "Scale9Height": 1,
            "TouchEnable": true,
            "AnchorPoint": {},
            "Position": {
              "X": 0.0,
              "Y": 0.0
            },
            "Scale": {
              "ScaleX": 1.0,
              "ScaleY": 1.0
            },
            "CColor": {},
            "IconVisible": false,
            "PrePosition": {
              "X": 0.0,
              "Y": 0.0
            },
            "PreSize": {
              "X": 1.0,
              "Y": 1.0
            },
            "Tag": 416,
            "Children": [
              {
                "FileData": {
                  "Type": "Normal",
                  "Path": "mainUI/bg_05.png",
                  "Plist": ""
                },
                "Scale9Enable": true,
                "Scale9OriginX": 13,
                "Scale9OriginY": 13,
                "Scale9Width": 5,
                "Scale9Height": 6,
                "AnchorPoint": {},
                "Position": {
                  "X": 0.0,
                  "Y": 0.0
                },
                "Scale": {
                  "ScaleX": 1.0,
                  "ScaleY": 1.0
                },
                "CColor": {},
                "IconVisible": false,
                "PrePosition": {
                  "X": 0.0,
                  "Y": 0.0
                },
                "PreSize": {
                  "X": 1.0,
                  "Y": 1.0
                },
                "Tag": 384,
                "ActionTag": 1402301482,
                "Size": {
                  "X": 580.0,
                  "Y": 100.0
                },
                "Name": "bg",
                "ctype": "ImageViewObjectData"
              },
              {
                "FileData": {
                  "Type": "Normal",
                  "Path": "mainUI/hero_icon.png",
                  "Plist": ""
                },
                "Scale9Width": 90,
                "Scale9Height": 90,
                "AnchorPoint": {
                  "ScaleX": 0.5,
                  "ScaleY": 0.5
                },
                "Position": {
                  "X": 68.7928,
                  "Y": 50.1295
                },
                "Scale": {
                  "ScaleX": 1.0,
                  "ScaleY": 1.0
                },
                "CColor": {},
                "IconVisible": false,
                "PrePosition": {
                  "X": 0.1186,
                  "Y": 0.5013
                },
                "PreSize": {
                  "X": 0.1552,
                  "Y": 0.9
                },
                "LeftMargin": 23.7928,
                "RightMargin": 466.2072,
                "TopMargin": 4.8705,
                "BottomMargin": 5.1295,
                "Tag": 39,
                "ActionTag": 679581239,
                "Size": {
                  "X": 90.0,
                  "Y": 90.0
                },
                "Name": "player_icon",
                "ctype": "ImageViewObjectData"
              },
              {
                "IsCustomSize": true,
                "FontSize": 20,
                "LabelText": "玩家名字六字",
                "VerticalAlignmentType": "VT_Center",
                "OutlineColor": {
                  "G": 0,
                  "B": 0
                },
                "ShadowColor": {
                  "R": 110,
                  "G": 110,
                  "B": 110
                },
                "ShadowOffsetX": 2.0,
                "ShadowOffsetY": -2.0,
                "AnchorPoint": {
                  "ScaleX": 0.5,
                  "ScaleY": 0.5
                },
                "Position": {
                  "X": 202.3848,
                  "Y": 74.7257
                },
                "Scale": {
                  "ScaleX": 1.0,
                  "ScaleY": 1.0
                },
                "CColor": {
                  "R": 0,
                  "G": 0,
                  "B": 0
                },
                "IconVisible": false,
                "PrePosition": {
                  "X": 0.3489,
                  "Y": 0.7473
                },
                "PreSize": {
                  "X": 0.2759,
                  "Y": 0.2
                },
                "LeftMargin": 122.3848,
                "RightMargin": 297.6152,
                "TopMargin": 15.2743,
                "BottomMargin": 64.7257,
                "Tag": 40,
                "ActionTag": -714092074,
                "Size": {
                  "X": 160.0,
                  "Y": 20.0
                },
                "Name": "player_name",
                "ctype": "TextObjectData"
              },
              {
                "IsCustomSize": true,
                "FontSize": 20,
                "LabelText": "Lv.999",
                "VerticalAlignmentType": "VT_Center",
                "OutlineColor": {
                  "G": 0,
                  "B": 0
                },
                "ShadowColor": {
                  "R": 110,
                  "G": 110,
                  "B": 110
                },
                "ShadowOffsetX": 2.0,
                "ShadowOffsetY": -2.0,
                "AnchorPoint": {
                  "ScaleX": 0.5,
                  "ScaleY": 0.5
                },
                "Position": {
                  "X": 202.3848,
                  "Y": 49.0894
                },
                "Scale": {
                  "ScaleX": 1.0,
                  "ScaleY": 1.0
                },
                "CColor": {
                  "R": 0,
                  "G": 0,
                  "B": 0
                },
                "IconVisible": false,
                "PrePosition": {
                  "X": 0.3489,
                  "Y": 0.4909
                },
                "PreSize": {
                  "X": 0.2759,
                  "Y": 0.2
                },
                "LeftMargin": 122.3848,
                "RightMargin": 297.6152,
                "TopMargin": 40.9106,
                "BottomMargin": 39.0894,
                "Tag": 41,
                "ActionTag": -1925350662,
                "Size": {
                  "X": 160.0,
                  "Y": 20.0
                },
                "Name": "player_lv",
                "ctype": "TextObjectData"
              },
              {
                "IsCustomSize": true,
                "FontSize": 20,
                "LabelText": "转生次数：99次",
                "VerticalAlignmentType": "VT_Center",
                "OutlineColor": {
                  "G": 0,
                  "B": 0
                },
                "ShadowColor": {
                  "R": 110,
                  "G": 110,
                  "B": 110
                },
                "ShadowOffsetX": 2.0,
                "ShadowOffsetY": -2.0,
                "AnchorPoint": {
                  "ScaleX": 0.5,
                  "ScaleY": 0.5
                },
                "Position": {
                  "X": 202.3848,
                  "Y": 23.4529
                },
                "Scale": {
                  "ScaleX": 1.0,
                  "ScaleY": 1.0
                },
                "CColor": {
                  "R": 0,
                  "G": 0,
                  "B": 0
                },
                "IconVisible": false,
                "PrePosition": {
                  "X": 0.3489,
                  "Y": 0.2345
                },
                "PreSize": {
                  "X": 0.2759,
                  "Y": 0.2
                },
                "LeftMargin": 122.3848,
                "RightMargin": 297.6152,
                "TopMargin": 66.5471,
                "BottomMargin": 13.4529,
                "Tag": 42,
                "ActionTag": -1997764095,
                "Size": {
                  "X": 160.0,
                  "Y": 20.0
                },
                "Name": "player_prestige",
                "ctype": "TextObjectData"
              },
              {
                "FileData": {
                  "Type": "Normal",
                  "Path": "rankUI/clearance_rank.png",
                  "Plist": ""
                },
                "Scale9Width": 247,
                "Scale9Height": 31,
                "AnchorPoint": {
                  "ScaleX": 0.5,
                  "ScaleY": 0.5
                },
                "Position": {
                  "X": 424.0123,
                  "Y": 52.1379
                },
                "Scale": {
                  "ScaleX": 1.0,
                  "ScaleY": 1.0
                },
                "CColor": {},
                "IconVisible": false,
                "PrePosition": {
                  "X": 0.7311,
                  "Y": 0.5214
                },
                "PreSize": {
                  "X": 0.4259,
                  "Y": 0.31
                },
                "LeftMargin": 300.5123,
                "RightMargin": 32.4877,
                "TopMargin": 32.3621,
                "BottomMargin": 36.6379,
                "Tag": 389,
                "ActionTag": 1684059057,
                "Size": {
                  "X": 247.0,
                  "Y": 31.0
                },
                "Name": "stage_rank",
                "ctype": "ImageViewObjectData"
              },
              {
                "FileData": {
                  "Type": "Normal",
                  "Path": "rankUI/pvp_rank.png",
                  "Plist": ""
                },
                "Scale9Width": 247,
                "Scale9Height": 31,
                "AnchorPoint": {
                  "ScaleX": 0.5,
                  "ScaleY": 0.5
                },
                "Position": {
                  "X": 424.0123,
                  "Y": 52.1379
                },
                "Scale": {
                  "ScaleX": 1.0,
                  "ScaleY": 1.0
                },
                "CColor": {},
                "IconVisible": false,
                "PrePosition": {
                  "X": 0.7311,
                  "Y": 0.5214
                },
                "PreSize": {
                  "X": 0.4259,
                  "Y": 0.31
                },
                "LeftMargin": 300.5123,
                "RightMargin": 32.4877,
                "TopMargin": 32.3621,
                "BottomMargin": 36.6379,
                "Tag": 390,
                "ActionTag": 788911233,
                "Size": {
                  "X": 247.0,
                  "Y": 31.0
                },
                "Name": "pvp_rank",
                "ctype": "ImageViewObjectData"
              },
              {
                "CharWidth": 21,
                "CharHeight": 21,
                "LabelText": "99",
                "StartChar": "0",
                "LabelAtlasFileImage_CNB": {
                  "Type": "Normal",
                  "Path": "mainUI/font28_yellow.png",
                  "Plist": ""
                },
                "AnchorPoint": {
                  "ScaleX": 0.5,
                  "ScaleY": 0.5
                },
                "Position": {
                  "X": 483.2911,
                  "Y": 52.8046
                },
                "Scale": {
                  "ScaleX": 1.0,
                  "ScaleY": 1.0
                },
                "CColor": {},
                "IconVisible": false,
                "PrePosition": {
                  "X": 0.8333,
                  "Y": 0.528
                },
                "PreSize": {
                  "X": 0.0724,
                  "Y": 0.21
                },
                "LeftMargin": 462.2911,
                "RightMargin": 75.7089,
                "TopMargin": 36.6954,
                "BottomMargin": 42.3046,
                "Tag": 391,
                "ActionTag": -536068057,
                "Size": {
                  "X": 42.0,
                  "Y": 21.0
                },
                "Name": "num",
                "ctype": "TextAtlasObjectData"
              }
            ],
            "ActionTag": 318411989,
            "Size": {
              "X": 580.0,
              "Y": 100.0
            },
            "Name": "root",
            "ctype": "PanelObjectData"
          }
        ],
        "Size": {
          "X": 580.0,
          "Y": 100.0
        },
        "Name": "Layer",
        "ctype": "LayerObjectData"
      },
      "UsedResources": [
        "mainUI/bg_05.png",
        "mainUI/font28_yellow.png",
        "mainUI/hero_icon.png",
        "rankUI/clearance_rank.png",
        "rankUI/pvp_rank.png"
      ],
      "ctype": "GameFileData"
    }
  },
  "Type": "Layer"
}